{"v":3,"stories":{"button--api":{"id":"button--api","title":"Button","name":"API","importPath":"./src/components/atoms/Button/index.stories.tsx"},"button--sizes":{"id":"button--sizes","title":"Button","name":"Sizes","importPath":"./src/components/atoms/Button/index.stories.tsx"},"button--variants":{"id":"button--variants","title":"Button","name":"Variants","importPath":"./src/components/atoms/Button/index.stories.tsx"},"button--elipse":{"id":"button--elipse","title":"Button","name":"Elipse","importPath":"./src/components/atoms/Button/index.stories.tsx"},"button--icon":{"id":"button--icon","title":"Button","name":"Icon","importPath":"./src/components/atoms/Button/index.stories.tsx"},"button--icon-only":{"id":"button--icon-only","title":"Button","name":"Icon Only","importPath":"./src/components/atoms/Button/index.stories.tsx"},"tabs--api":{"id":"tabs--api","title":"Tabs","name":"API","importPath":"./src/components/molecule/Tabs/index.stories.tsx"}}}
